tidyplots/__init__.py
tidyplots/palettes.py
tidyplots/plotnine.py
tidyplots/themes.py
tidyplots/tidyplots.py
tidyplots_python-0.1.0.dist-info/LICENSE
tidyplots_python-0.1.0.dist-info/METADATA
tidyplots_python-0.1.0.dist-info/WHEEL
tidyplots_python-0.1.0.dist-info/top_level.txt
tidyplots_python-0.1.0.dist-info/RECORD
