Metadata-Version: 2.1
Name: tidyplots-python
Version: 0.1.0
Summary: A Python implementation of R's tidyplots for creating publication-ready plots
Home-page: https://github.com/JNU-Tangyin/tidyplots-python
Author: Tangyin
Author-email: tangyin@jnu.edu.cn
Project-URL: Bug Reports, https://github.com/JNU-Tangyin/tidyplots-python/issues
Project-URL: Source, https://github.com/JNU-Tangyin/tidyplots-python
Project-URL: Documentation, https://github.com/JNU-Tangyin/tidyplots-python#readme
Keywords: data visualization,plotting,statistics,ggplot,tidyverse
Classifier: Development Status :: 4 - Beta
Classifier: Intended Audience :: Science/Research
Classifier: License :: OSI Approved :: MIT License
Classifier: Programming Language :: Python :: 3
Classifier: Programming Language :: Python :: 3.8
Classifier: Programming Language :: Python :: 3.9
Classifier: Programming Language :: Python :: 3.10
Classifier: Programming Language :: Python :: 3.11
Classifier: Topic :: Scientific/Engineering :: Visualization
Classifier: Topic :: Software Development :: Libraries :: Python Modules
Requires-Python: >=3.8
License-File: LICENSE
Requires-Dist: pandas>=1.0.0
Requires-Dist: plotnine>=0.10.0
Requires-Dist: numpy>=1.18.0
Requires-Dist: scipy>=1.4.0
Requires-Dist: scikit-misc>=0.1.4
Requires-Dist: statsmodels>=0.13.0
